[
  {
    "anonymous": false,
    "inputs": [
      {
        "indexed": false,
        "internalType": "address",
        "name": "previousAdmin",
        "type": "address"
      },
      {
        "indexed": false,
        "internalType": "address",
        "name": "newAdmin",
        "type": "address"
      }
    ],
    "name": "AdminChanged",
    "type": "event"
  },
  {
    "anonymous": false,
    "inputs": [
      {
        "indexed": true,
        "internalType": "address",
        "name": "beacon",
        "type": "address"
      }
    ],
    "name": "BeaconUpgraded",
    "type": "event"
  },
  {
    "anonymous": false,
    "inputs": [
      {
        "indexed": true,
        "internalType": "address",
        "name": "owner",
        "type": "address"
      },
      {
        "indexed": false,
        "internalType": "address",
        "name": "extension",
        "type": "address"
      },
      {
        "indexed": false,
        "internalType": "address",
        "name": "creator",
        "type": "address"
      }
    ],
    "name": "ExtensionCreated",
    "type": "event"
  },
  {
    "anonymous": false,
    "inputs": [
      {
        "indexed": false,
        "internalType": "uint8",
        "name": "version",
        "type": "uint8"
      }
    ],
    "name": "Initialized",
    "type": "event"
  },
  {
    "anonymous": false,
    "inputs": [
      {
        "indexed": true,
        "internalType": "address",
        "name": "owner",
        "type": "address"
      },
      {
        "indexed": false,
        "internalType": "address",
        "name": "newToken",
        "type": "address"
      },
      {
        "indexed": false,
        "internalType": "bool",
        "name": "lazy",
        "type": "bool"
      },
      {
        "indexed": false,
        "internalType": "bool",
        "name": "is721",
        "type": "bool"
      }
    ],
    "name": "TokenCreated",
    "type": "event"
  },
  {
    "anonymous": false,
    "inputs": [
      {
        "indexed": true,
        "internalType": "address",
        "name": "implementation",
        "type": "address"
      }
    ],
    "name": "Upgraded",
    "type": "event"
  },
  {
    "inputs": [
      { "internalType": "address", "name": "creator", "type": "address" }
    ],
    "name": "createExtension",
    "outputs": [],
    "stateMutability": "nonpayable",
    "type": "function"
  },
  {
    "inputs": [
      { "internalType": "bool", "name": "isERC721", "type": "bool" },
      { "internalType": "string", "name": "name", "type": "string" },
      { "internalType": "string", "name": "symbol", "type": "string" },
      { "internalType": "bool", "name": "lazy", "type": "bool" }
    ],
    "name": "createToken",
    "outputs": [],
    "stateMutability": "nonpayable",
    "type": "function"
  },
  {
    "inputs": [],
    "name": "erc1155ProxyImplAddress",
    "outputs": [{ "internalType": "address", "name": "", "type": "address" }],
    "stateMutability": "view",
    "type": "function"
  },
  {
    "inputs": [],
    "name": "erc721ProxyImplAddress",
    "outputs": [{ "internalType": "address", "name": "", "type": "address" }],
    "stateMutability": "view",
    "type": "function"
  },
  {
    "inputs": [
      {
        "internalType": "address",
        "name": "_erc721ProxyImplAddress",
        "type": "address"
      },
      {
        "internalType": "address",
        "name": "_erc1155ProxyImplAddress",
        "type": "address"
      },
      {
        "internalType": "address",
        "name": "_lazyERC721ProxyImplAddress",
        "type": "address"
      },
      {
        "internalType": "address",
        "name": "_lazyERC1155ProxyImplAddress",
        "type": "address"
      }
    ],
    "name": "initialize",
    "outputs": [],
    "stateMutability": "nonpayable",
    "type": "function"
  },
  {
    "inputs": [],
    "name": "lazyERC1155ProxyImplAddress",
    "outputs": [{ "internalType": "address", "name": "", "type": "address" }],
    "stateMutability": "view",
    "type": "function"
  },
  {
    "inputs": [],
    "name": "lazyERC721ProxyImplAddress",
    "outputs": [{ "internalType": "address", "name": "", "type": "address" }],
    "stateMutability": "view",
    "type": "function"
  },
  {
    "inputs": [],
    "name": "proxiableUUID",
    "outputs": [{ "internalType": "bytes32", "name": "", "type": "bytes32" }],
    "stateMutability": "view",
    "type": "function"
  },
  {
    "inputs": [
      {
        "internalType": "address",
        "name": "newImplementation",
        "type": "address"
      }
    ],
    "name": "upgradeTo",
    "outputs": [],
    "stateMutability": "nonpayable",
    "type": "function"
  },
  {
    "inputs": [
      {
        "internalType": "address",
        "name": "newImplementation",
        "type": "address"
      },
      { "internalType": "bytes", "name": "data", "type": "bytes" }
    ],
    "name": "upgradeToAndCall",
    "outputs": [],
    "stateMutability": "payable",
    "type": "function"
  }
]
